simplest_logger
