Metadata-Version: 1.1
Name: simplest-logger
Version: 1.1
Summary: Simplest logger you've ever seen (probably)
Home-page: https://github.com/megahomyak/simplest_logger
Author: megahomyak
Author-email: g.megahomyak@gmail.com
License: GPL-3.0
Download-URL: https://github.com/megahomyak/simplest_logger/archive/v1.1.tar.gz
Platform: UNKNOWN
